LICENSE
README.md
setup.cfg
setup.py
RupineWeb3Utils/__init__.py
RupineWeb3Utils/rupine_api/__init__.py
RupineWeb3Utils/rupine_api/credentials.py
RupineWeb3Utils/rupine_api/keywordConfig.py
RupineWeb3Utils/rupine_api/tokenBacklog.py
RupineWeb3Utils/rupine_api/tokenMetaData.py
RupineWeb3Utils/slack/SlackPost.py
RupineWeb3Utils/slack/__init__.py
RupineWeb3Utils/utils/ObjToken.py
RupineWeb3Utils/utils/__init__.py
RupineWeb3Utils/utils/helper.py
RupineWeb3Utils/web3_utils/Honeypot.py
RupineWeb3Utils/web3_utils/__init__.py
RupineWeb3Utils/web3_utils/web3_checker.py
RupineWeb3Utils/web3_utils/web3_generic.py
RupineWeb3Utils/web3_utils/web3_globals.py
RupineWeb3Utils/web3_utils/web3_provider.py
RupineWeb3Utils/web3_utils/web3_txScan.py
RupineWeb3Utils/web3_utils/web3_uniswapV2.py
RupineWeb3Utils/web3_utils/web3_uniswapV3.py
rupineWeb3Utils.egg-info/PKG-INFO
rupineWeb3Utils.egg-info/SOURCES.txt
rupineWeb3Utils.egg-info/dependency_links.txt
rupineWeb3Utils.egg-info/requires.txt
rupineWeb3Utils.egg-info/top_level.txt